Package/__.init__.py
PM_AI-0.1.dist-info/METADATA
PM_AI-0.1.dist-info/WHEEL
PM_AI-0.1.dist-info/top_level.txt
PM_AI-0.1.dist-info/RECORD
